LICENSE
README.md
myrmex/__init__.py
myrmex/crawlers.py
myrmex-0.1.5.dist-info/METADATA
myrmex-0.1.5.dist-info/WHEEL
myrmex-0.1.5.dist-info/licenses/LICENSE
myrmex-0.1.5.dist-info/RECORD
