Metadata-Version: 2.4
Name: myrmex
Version: 0.1.5
Summary: The compact web crawling toolkit
Project-URL: Homepage, https://github.com/mrprfrm/myrmex
Author-email: Anton Petrov <mrprfrm@gmail.com>
License-File: LICENSE
Classifier: Intended Audience :: Developers
Classifier: Programming Language :: Python :: 3
Classifier: Topic :: Internet :: WWW/HTTP
Classifier: Typing :: Typed
Requires-Python: >=3.9
Requires-Dist: aiohttp-socks>=0.10.1
Requires-Dist: aiohttp>=3.10.11
Requires-Dist: result>=0.17.0
Requires-Dist: stem>=1.8.2
